kxy_codew/__init__.py
kxy_codew/config.py
kxy_codew/memory.py
kxy_codew/performance.py
kxy_codew/state.py
kxy_codew/watchman.py
kxy_codew-0.1.352.dist-info/METADATA
kxy_codew-0.1.352.dist-info/WHEEL
kxy_codew-0.1.352.dist-info/RECORD
