Metadata-Version: 2.4
Name: kxy_codew
Version: 0.1.352
Summary: KXY, a package for profiling remotely
Project-URL: Homepage, https://github.com/codew-io/kxy
Project-URL: Issues, https://github.com/codew-io/kxy/issues
Author-email: Jhoubert Rincon <jhoubert@codew.es>
Classifier: Operating System :: OS Independent
Classifier: Programming Language :: Python :: 3
Requires-Python: >=3.9
